seesus/SDG_desc.py
seesus/SDG_keys.py
seesus/__init__.py
seesus/see_keys.py
seesus/seesus.py
seesus-1.2.1.dist-info/LICENSE
seesus-1.2.1.dist-info/METADATA
seesus-1.2.1.dist-info/WHEEL
seesus-1.2.1.dist-info/top_level.txt
seesus-1.2.1.dist-info/RECORD
