Metadata-Version: 2.1
Name: seesus
Version: 1.2.1
Summary: a social, environmental, and economic sustainability classifier based on the UN Sustainable Development Goals
Author-email: Meng Cai <mengcai24601@gmail.com>, Yingjie Li <yingjieli.edu@gmail.com>, Dirk Colbry <colbrydi@msu.edu>, Veronica Frans <verofrans@gmail.com>, Yuqian Zhang <zhan1364@msu.edu>
License: GPL-3.0
Keywords: sustainability,SDG,sustainable-development-goals,classification,regular expressions,text mining
Requires-Python: >=3.7
License-File: LICENSE
Requires-Dist: regex
Provides-Extra: doc
Requires-Dist: pdoc3 ; extra == 'doc'
Provides-Extra: test
Requires-Dist: pytest ; extra == 'test'
